{
    "collection": [
        {
            "id": 1,
            "type": "conmemorativas",
            "year": "2004",
            "country": "finlandia"
        },
        {
            "id": 2,
            "type": "conmemorativas",
            "year": "2004",
            "country": "grecia"
        },
        {
            "id": 3,
            "type": "conmemorativas",
            "year": "2004",
            "country": "italia"
        },
        {
            "id": 4,
            "type": "conmemorativas",
            "year": "2004",
            "country": "luxemburgo"
        },
        {
            "id": 5,
            "type": "conmemorativas",
            "year": "2004",
            "country": "san_marino"
        },
        {
            "id": 6,
            "type": "conmemorativas",
            "year": "2004",
            "country": "vaticano"
        },
        {
            "id": 7,
            "type": "conmemorativas",
            "year": "2005",
            "country": "austria"
        },
        {
            "id": 8,
            "type": "conmemorativas",
            "year": "2005",
            "country": "belgica"
        },
        {
            "id": 9,
            "type": "conmemorativas",
            "year": "2005",
            "country": "españa"
        },
        {
            "id": 10,
            "type": "conmemorativas",
            "year": "2005",
            "country": "finlandia"
        },
        {
            "id": 11,
            "type": "conmemorativas",
            "year": "2005",
            "country": "italia"
        },
        {
            "id": 12,
            "type": "conmemorativas",
            "year": "2005",
            "country": "luxemburgo"
        },
        {
            "id": 13,
            "type": "conmemorativas",
            "year": "2005",
            "country": "san_marino"
        },
        {
            "id": 14,
            "type": "conmemorativas",
            "year": "2005",
            "country": "vaticano"
        },
        {
            "id": 15,
            "type": "conmemorativas",
            "year": "2006",
            "country": "alemania"
        },
        {
            "id": 16,
            "type": "conmemorativas",
            "year": "2006",
            "country": "belgica"
        },
        {
            "id": 17,
            "type": "conmemorativas",
            "year": "2006",
            "country": "finlandia"
        },
        {
            "id": 18,
            "type": "conmemorativas",
            "year": "2006",
            "country": "italia"
        },
        {
            "id": 19,
            "type": "conmemorativas",
            "year": "2006",
            "country": "luxemburgo"
        },
        {
            "id": 20,
            "type": "conmemorativas",
            "year": "2006",
            "country": "san_marino"
        },
        {
            "id": 21,
            "type": "conmemorativas",
            "year": "2006",
            "country": "vaticano"
        },
        {
            "id": 22,
            "type": "conmemorativas",
            "year": "2007",
            "country": "alemania"
        },
        {
            "id": 23,
            "type": "conmemorativas",
            "year": "2007",
            "country": "alemania_2"
        },
        {
            "id": 24,
            "type": "conmemorativas",
            "year": "2007",
            "country": "austria"
        },
        {
            "id": 25,
            "type": "conmemorativas",
            "year": "2007",
            "country": "belgica"
        },
        {
            "id": 26,
            "type": "conmemorativas",
            "year": "2007",
            "country": "eslovenia"
        },
        {
            "id": 27,
            "type": "conmemorativas",
            "year": "2007",
            "country": "españa"
        },
        {
            "id": 28,
            "type": "conmemorativas",
            "year": "2007",
            "country": "finlandia"
        },
        {
            "id": 29,
            "type": "conmemorativas",
            "year": "2007",
            "country": "finlandia_2"
        },
        {
            "id": 30,
            "type": "conmemorativas",
            "year": "2007",
            "country": "francia"
        },
        {
            "id": 31,
            "type": "conmemorativas",
            "year": "2007",
            "country": "grecia"
        },
        {
            "id": 32,
            "type": "conmemorativas",
            "year": "2007",
            "country": "irlanda"
        },
        {
            "id": 33,
            "type": "conmemorativas",
            "year": "2007",
            "country": "italia"
        },
        {
            "id": 34,
            "type": "conmemorativas",
            "year": "2007",
            "country": "luxemburgo"
        },
        {
            "id": 35,
            "type": "conmemorativas",
            "year": "2007",
            "country": "luxemburgo_2"
        },
        {
            "id": 36,
            "type": "conmemorativas",
            "year": "2007",
            "country": "monaco"
        },
        {
            "id": 37,
            "type": "conmemorativas",
            "year": "2007",
            "country": "paises_bajos"
        },
        {
            "id": 38,
            "type": "conmemorativas",
            "year": "2007",
            "country": "portugal"
        },
        {
            "id": 39,
            "type": "conmemorativas",
            "year": "2007",
            "country": "portugal_2"
        },
        {
            "id": 40,
            "type": "conmemorativas",
            "year": "2007",
            "country": "san_marino"
        },
        {
            "id": 41,
            "type": "conmemorativas",
            "year": "2007",
            "country": "vaticano"
        },
        {
            "id": 42,
            "type": "conmemorativas",
            "year": "2008",
            "country": "alemania"
        },
        {
            "id": 43,
            "type": "conmemorativas",
            "year": "2008",
            "country": "belgica"
        },
        {
            "id": 44,
            "type": "conmemorativas",
            "year": "2008",
            "country": "eslovenia"
        },
        {
            "id": 45,
            "type": "conmemorativas",
            "year": "2008",
            "country": "finlandia"
        },
        {
            "id": 46,
            "type": "conmemorativas",
            "year": "2008",
            "country": "francia"
        },
        {
            "id": 47,
            "type": "conmemorativas",
            "year": "2008",
            "country": "italia"
        },
        {
            "id": 48,
            "type": "conmemorativas",
            "year": "2008",
            "country": "luxemburgo"
        },
        {
            "id": 49,
            "type": "conmemorativas",
            "year": "2008",
            "country": "portugal"
        },
        {
            "id": 50,
            "type": "conmemorativas",
            "year": "2008",
            "country": "san_marino"
        },
        {
            "id": 51,
            "type": "conmemorativas",
            "year": "2008",
            "country": "vaticano"
        },
        {
            "id": 52,
            "type": "conmemorativas",
            "year": "2009",
            "country": "alemania"
        },
        {
            "id": 53,
            "type": "conmemorativas",
            "year": "2009",
            "country": "alemania_2"
        },
        {
            "id": 54,
            "type": "conmemorativas",
            "year": "2009",
            "country": "austria"
        },
        {
            "id": 55,
            "type": "conmemorativas",
            "year": "2009",
            "country": "belgica"
        },
        {
            "id": 56,
            "type": "conmemorativas",
            "year": "2009",
            "country": "belgica_2"
        },
        {
            "id": 57,
            "type": "conmemorativas",
            "year": "2009",
            "country": "chipre_2"
        },
        {
            "id": 58,
            "type": "conmemorativas",
            "year": "2009",
            "country": "eslovaquia"
        },
        {
            "id": 59,
            "type": "conmemorativas",
            "year": "2009",
            "country": "eslovaquia_2"
        },
        {
            "id": 60,
            "type": "conmemorativas",
            "year": "2009",
            "country": "eslovenia_2"
        },
        {
            "id": 61,
            "type": "conmemorativas",
            "year": "2009",
            "country": "españa_2"
        },
        {
            "id": 62,
            "type": "conmemorativas",
            "year": "2009",
            "country": "finlandia"
        },
        {
            "id": 63,
            "type": "conmemorativas",
            "year": "2009",
            "country": "finlandia_2"
        },
        {
            "id": 64,
            "type": "conmemorativas",
            "year": "2009",
            "country": "francia_2"
        },
        {
            "id": 65,
            "type": "conmemorativas",
            "year": "2009",
            "country": "grecia_2"
        },
        {
            "id": 66,
            "type": "conmemorativas",
            "year": "2009",
            "country": "irlanda_2"
        },
        {
            "id": 67,
            "type": "conmemorativas",
            "year": "2009",
            "country": "italia"
        },
        {
            "id": 68,
            "type": "conmemorativas",
            "year": "2009",
            "country": "italia_2"
        },
        {
            "id": 69,
            "type": "conmemorativas",
            "year": "2009",
            "country": "luxemburgo"
        },
        {
            "id": 70,
            "type": "conmemorativas",
            "year": "2009",
            "country": "luxemburgo_2"
        },
        {
            "id": 71,
            "type": "conmemorativas",
            "year": "2009",
            "country": "luxemburgo_3"
        },
        {
            "id": 72,
            "type": "conmemorativas",
            "year": "2009",
            "country": "malta_2"
        },
        {
            "id": 73,
            "type": "conmemorativas",
            "year": "2009",
            "country": "paises_bajos_2"
        },
        {
            "id": 74,
            "type": "conmemorativas",
            "year": "2009",
            "country": "portugal"
        },
        {
            "id": 75,
            "type": "conmemorativas",
            "year": "2009",
            "country": "portugal_2"
        },
        {
            "id": 76,
            "type": "conmemorativas",
            "year": "2009",
            "country": "san_marino"
        },
        {
            "id": 77,
            "type": "conmemorativas",
            "year": "2009",
            "country": "vaticano"
        },
        {
            "id": 78,
            "type": "conmemorativas",
            "year": "2010",
            "country": "alemania"
        },
        {
            "id": 79,
            "type": "conmemorativas",
            "year": "2010",
            "country": "belgica"
        },
        {
            "id": 80,
            "type": "conmemorativas",
            "year": "2010",
            "country": "eslovenia"
        },
        {
            "id": 81,
            "type": "conmemorativas",
            "year": "2010",
            "country": "españa"
        },
        {
            "id": 82,
            "type": "conmemorativas",
            "year": "2010",
            "country": "finlandia"
        },
        {
            "id": 83,
            "type": "conmemorativas",
            "year": "2010",
            "country": "francia"
        },
        {
            "id": 84,
            "type": "conmemorativas",
            "year": "2010",
            "country": "grecia"
        },
        {
            "id": 85,
            "type": "conmemorativas",
            "year": "2010",
            "country": "italia"
        },
        {
            "id": 86,
            "type": "conmemorativas",
            "year": "2010",
            "country": "luxemburgo"
        },
        {
            "id": 87,
            "type": "conmemorativas",
            "year": "2010",
            "country": "portugal"
        },
        {
            "id": 88,
            "type": "conmemorativas",
            "year": "2010",
            "country": "san_marino"
        },
        {
            "id": 89,
            "type": "conmemorativas",
            "year": "2010",
            "country": "vaticano"
        },
        {
            "id": 90,
            "type": "conmemorativas",
            "year": "2011",
            "country": "alemania"
        },
        {
            "id": 91,
            "type": "conmemorativas",
            "year": "2011",
            "country": "belgica"
        },
        {
            "id": 92,
            "type": "conmemorativas",
            "year": "2011",
            "country": "eslovaquia"
        },
        {
            "id": 93,
            "type": "conmemorativas",
            "year": "2011",
            "country": "eslovenia"
        },
        {
            "id": 94,
            "type": "conmemorativas",
            "year": "2011",
            "country": "españa"
        },
        {
            "id": 95,
            "type": "conmemorativas",
            "year": "2011",
            "country": "finlandia"
        },
        {
            "id": 96,
            "type": "conmemorativas",
            "year": "2011",
            "country": "francia"
        },
        {
            "id": 97,
            "type": "conmemorativas",
            "year": "2011",
            "country": "grecia"
        },
        {
            "id": 98,
            "type": "conmemorativas",
            "year": "2011",
            "country": "italia"
        },
        {
            "id": 99,
            "type": "conmemorativas",
            "year": "2011",
            "country": "luxemburgo"
        },
        {
            "id": 100,
            "type": "conmemorativas",
            "year": "2011",
            "country": "malta"
        },
        {
            "id": 101,
            "type": "conmemorativas",
            "year": "2011",
            "country": "monaco"
        },
        {
            "id": 102,
            "type": "conmemorativas",
            "year": "2011",
            "country": "paises_bajos"
        },
        {
            "id": 103,
            "type": "conmemorativas",
            "year": "2011",
            "country": "portugal"
        },
        {
            "id": 104,
            "type": "conmemorativas",
            "year": "2011",
            "country": "san_marino"
        },
        {
            "id": 105,
            "type": "conmemorativas",
            "year": "2011",
            "country": "vaticano"
        },
        {
            "id": 106,
            "type": "conmemorativas",
            "year": "2012",
            "country": "alemania"
        },
        {
            "id": 107,
            "type": "conmemorativas",
            "year": "2012",
            "country": "alemania_2"
        },
        {
            "id": 108,
            "type": "conmemorativas",
            "year": "2012",
            "country": "austria"
        },
        {
            "id": 109,
            "type": "conmemorativas",
            "year": "2012",
            "country": "belgica"
        },
        {
            "id": 110,
            "type": "conmemorativas",
            "year": "2012",
            "country": "belgica_2"
        },
        {
            "id": 111,
            "type": "conmemorativas",
            "year": "2012",
            "country": "chipre"
        },
        {
            "id": 112,
            "type": "conmemorativas",
            "year": "2012",
            "country": "eslovaquia"
        },
        {
            "id": 113,
            "type": "conmemorativas",
            "year": "2012",
            "country": "eslovenia_2"
        },
        {
            "id": 114,
            "type": "conmemorativas",
            "year": "2012",
            "country": "españa"
        },
        {
            "id": 115,
            "type": "conmemorativas",
            "year": "2012",
            "country": "españa_2"
        },
        {
            "id": 116,
            "type": "conmemorativas",
            "year": "2012",
            "country": "estonia"
        },
        {
            "id": 117,
            "type": "conmemorativas",
            "year": "2012",
            "country": "finlandia"
        },
        {
            "id": 118,
            "type": "conmemorativas",
            "year": "2012",
            "country": "finlandia_2"
        },
        {
            "id": 119,
            "type": "conmemorativas",
            "year": "2012",
            "country": "francia"
        },
        {
            "id": 120,
            "type": "conmemorativas",
            "year": "2012",
            "country": "francia_2"
        },
        {
            "id": 121,
            "type": "conmemorativas",
            "year": "2012",
            "country": "grecia_2"
        },
        {
            "id": 122,
            "type": "conmemorativas",
            "year": "2012",
            "country": "irlanda_2"
        },
        {
            "id": 123,
            "type": "conmemorativas",
            "year": "2012",
            "country": "italia"
        },
        {
            "id": 124,
            "type": "conmemorativas",
            "year": "2012",
            "country": "italia_2"
        },
        {
            "id": 125,
            "type": "conmemorativas",
            "year": "2012",
            "country": "luxemburgo"
        },
        {
            "id": 126,
            "type": "conmemorativas",
            "year": "2012",
            "country": "luxemburgo_2"
        },
        {
            "id": 127,
            "type": "conmemorativas",
            "year": "2012",
            "country": "luxemburgo_3"
        },
        {
            "id": 128,
            "type": "conmemorativas",
            "year": "2012",
            "country": "malta"
        },
        {
            "id": 129,
            "type": "conmemorativas",
            "year": "2012",
            "country": "malta_2"
        },
        {
            "id": 130,
            "type": "conmemorativas",
            "year": "2012",
            "country": "monaco"
        },
        {
            "id": 131,
            "type": "conmemorativas",
            "year": "2012",
            "country": "paises_bajos"
        },
        {
            "id": 132,
            "type": "conmemorativas",
            "year": "2012",
            "country": "portugal"
        },
        {
            "id": 133,
            "type": "conmemorativas",
            "year": "2012",
            "country": "portugal_2"
        },
        {
            "id": 134,
            "type": "conmemorativas",
            "year": "2012",
            "country": "san_marino"
        },
        {
            "id": 135,
            "type": "conmemorativas",
            "year": "2012",
            "country": "vaticano"
        },
        {
            "id": 136,
            "type": "conmemorativas",
            "year": "2013",
            "country": "alemania"
        },
        {
            "id": 137,
            "type": "conmemorativas",
            "year": "2013",
            "country": "alemania_2"
        },
        {
            "id": 138,
            "type": "conmemorativas",
            "year": "2013",
            "country": "belgica"
        },
        {
            "id": 139,
            "type": "conmemorativas",
            "year": "2013",
            "country": "eslovaquia"
        },
        {
            "id": 140,
            "type": "conmemorativas",
            "year": "2013",
            "country": "eslovenia"
        },
        {
            "id": 141,
            "type": "conmemorativas",
            "year": "2013",
            "country": "españa"
        },
        {
            "id": 142,
            "type": "conmemorativas",
            "year": "2013",
            "country": "finlandia"
        },
        {
            "id": 143,
            "type": "conmemorativas",
            "year": "2013",
            "country": "finlandia_2"
        },
        {
            "id": 144,
            "type": "conmemorativas",
            "year": "2013",
            "country": "francia"
        },
        {
            "id": 145,
            "type": "conmemorativas",
            "year": "2013",
            "country": "francia_2"
        },
        {
            "id": 146,
            "type": "conmemorativas",
            "year": "2013",
            "country": "grecia"
        },
        {
            "id": 147,
            "type": "conmemorativas",
            "year": "2013",
            "country": "grecia_2"
        },
        {
            "id": 148,
            "type": "conmemorativas",
            "year": "2013",
            "country": "italia"
        },
        {
            "id": 149,
            "type": "conmemorativas",
            "year": "2013",
            "country": "italia_2"
        },
        {
            "id": 150,
            "type": "conmemorativas",
            "year": "2013",
            "country": "luxemburgo"
        },
        {
            "id": 151,
            "type": "conmemorativas",
            "year": "2013",
            "country": "malta"
        },
        {
            "id": 152,
            "type": "conmemorativas",
            "year": "2013",
            "country": "monaco"
        },
        {
            "id": 153,
            "type": "conmemorativas",
            "year": "2013",
            "country": "paises_bajos"
        },
        {
            "id": 154,
            "type": "conmemorativas",
            "year": "2013",
            "country": "paises_bajos_2"
        },
        {
            "id": 155,
            "type": "conmemorativas",
            "year": "2013",
            "country": "portugal"
        },
        {
            "id": 156,
            "type": "conmemorativas",
            "year": "2013",
            "country": "san_marino"
        },
        {
            "id": 157,
            "type": "conmemorativas",
            "year": "2013",
            "country": "vaticano"
        },
        {
            "id": 158,
            "type": "conmemorativas",
            "year": "2013",
            "country": "vaticano_2"
        },
        {
            "id": 159,
            "type": "conmemorativas",
            "year": "2014",
            "country": "alemania_2"
        },
        {
            "id": 160,
            "type": "conmemorativas",
            "year": "2014",
            "country": "andorra"
        },
        {
            "id": 161,
            "type": "conmemorativas",
            "year": "2014",
            "country": "belgica"
        },
        {
            "id": 162,
            "type": "conmemorativas",
            "year": "2014",
            "country": "belgica_2"
        },
        {
            "id": 163,
            "type": "conmemorativas",
            "year": "2014",
            "country": "eslovaquia"
        },
        {
            "id": 164,
            "type": "conmemorativas",
            "year": "2014",
            "country": "eslovenia"
        },
        {
            "id": 165,
            "type": "conmemorativas",
            "year": "2014",
            "country": "españa"
        },
        {
            "id": 166,
            "type": "conmemorativas",
            "year": "2014",
            "country": "españa_2"
        },
        {
            "id": 167,
            "type": "conmemorativas",
            "year": "2014",
            "country": "finlandia"
        },
        {
            "id": 168,
            "type": "conmemorativas",
            "year": "2014",
            "country": "finlandia_2"
        },
        {
            "id": 169,
            "type": "conmemorativas",
            "year": "2014",
            "country": "francia"
        },
        {
            "id": 170,
            "type": "conmemorativas",
            "year": "2014",
            "country": "francia_2"
        },
        {
            "id": 171,
            "type": "conmemorativas",
            "year": "2014",
            "country": "grecia"
        },
        {
            "id": 172,
            "type": "conmemorativas",
            "year": "2014",
            "country": "grecia_2"
        },
        {
            "id": 173,
            "type": "conmemorativas",
            "year": "2014",
            "country": "italia"
        },
        {
            "id": 174,
            "type": "conmemorativas",
            "year": "2014",
            "country": "italia_2"
        },
        {
            "id": 175,
            "type": "conmemorativas",
            "year": "2014",
            "country": "letonia"
        },
        {
            "id": 176,
            "type": "conmemorativas",
            "year": "2014",
            "country": "luxemburgo"
        },
        {
            "id": 177,
            "type": "conmemorativas",
            "year": "2014",
            "country": "luxemburgo_2"
        },
        {
            "id": 178,
            "type": "conmemorativas",
            "year": "2014",
            "country": "malta"
        },
        {
            "id": 179,
            "type": "conmemorativas",
            "year": "2014",
            "country": "malta_2"
        },
        {
            "id": 180,
            "type": "conmemorativas",
            "year": "2014",
            "country": "paises_bajos"
        },
        {
            "id": 181,
            "type": "conmemorativas",
            "year": "2014",
            "country": "portugal"
        },
        {
            "id": 182,
            "type": "conmemorativas",
            "year": "2014",
            "country": "portugal_2"
        },
        {
            "id": 183,
            "type": "conmemorativas",
            "year": "2014",
            "country": "san_marino"
        },
        {
            "id": 184,
            "type": "conmemorativas",
            "year": "2014",
            "country": "san_marino_2"
        },
        {
            "id": 185,
            "type": "conmemorativas",
            "year": "2014",
            "country": "vaticano"
        },
        {
            "id": 186,
            "type": "conmemorativas",
            "year": "2015",
            "country": "alemania"
        },
        {
            "id": 187,
            "type": "conmemorativas",
            "year": "2015",
            "country": "alemania_2"
        },
        {
            "id": 188,
            "type": "conmemorativas",
            "year": "2015",
            "country": "alemania_3"
        },
        {
            "id": 189,
            "type": "conmemorativas",
            "year": "2015",
            "country": "andorra"
        },
        {
            "id": 190,
            "type": "conmemorativas",
            "year": "2015",
            "country": "andorra_2"
        },
        {
            "id": 191,
            "type": "conmemorativas",
            "year": "2015",
            "country": "austria"
        },
        {
            "id": 192,
            "type": "conmemorativas",
            "year": "2015",
            "country": "belgica"
        },
        {
            "id": 193,
            "type": "conmemorativas",
            "year": "2015",
            "country": "belgica_2"
        },
        {
            "id": 194,
            "type": "conmemorativas",
            "year": "2015",
            "country": "chipre"
        },
        {
            "id": 195,
            "type": "conmemorativas",
            "year": "2015",
            "country": "eslovaquia"
        },
        {
            "id": 196,
            "type": "conmemorativas",
            "year": "2015",
            "country": "eslovaquia_2"
        },
        {
            "id": 197,
            "type": "conmemorativas",
            "year": "2015",
            "country": "eslovenia"
        },
        {
            "id": 198,
            "type": "conmemorativas",
            "year": "2015",
            "country": "eslovenia_2"
        },
        {
            "id": 199,
            "type": "conmemorativas",
            "year": "2015",
            "country": "españa"
        },
        {
            "id": 200,
            "type": "conmemorativas",
            "year": "2015",
            "country": "españa_2"
        },
        {
            "id": 201,
            "type": "conmemorativas",
            "year": "2015",
            "country": "estonia"
        },
        {
            "id": 202,
            "type": "conmemorativas",
            "year": "2015",
            "country": "finlandia"
        },
        {
            "id": 203,
            "type": "conmemorativas",
            "year": "2015",
            "country": "finlandia_2"
        },
        {
            "id": 204,
            "type": "conmemorativas",
            "year": "2015",
            "country": "finlandia_3"
        },
        {
            "id": 205,
            "type": "conmemorativas",
            "year": "2015",
            "country": "francia_2"
        },
        {
            "id": 206,
            "type": "conmemorativas",
            "year": "2015",
            "country": "francia_3"
        },
        {
            "id": 207,
            "type": "conmemorativas",
            "year": "2015",
            "country": "francia_4"
        },
        {
            "id": 208,
            "type": "conmemorativas",
            "year": "2015",
            "country": "grecia"
        },
        {
            "id": 209,
            "type": "conmemorativas",
            "year": "2015",
            "country": "grecia_2"
        },
        {
            "id": 210,
            "type": "conmemorativas",
            "year": "2015",
            "country": "irlanda"
        },
        {
            "id": 211,
            "type": "conmemorativas",
            "year": "2015",
            "country": "italia"
        },
        {
            "id": 212,
            "type": "conmemorativas",
            "year": "2015",
            "country": "italia_2"
        },
        {
            "id": 213,
            "type": "conmemorativas",
            "year": "2015",
            "country": "italia_3"
        },
        {
            "id": 214,
            "type": "conmemorativas",
            "year": "2015",
            "country": "letonia"
        },
        {
            "id": 215,
            "type": "conmemorativas",
            "year": "2015",
            "country": "letonia_2"
        },
        {
            "id": 216,
            "type": "conmemorativas",
            "year": "2015",
            "country": "letonia_3"
        },
        {
            "id": 217,
            "type": "conmemorativas",
            "year": "2015",
            "country": "lituania"
        },
        {
            "id": 218,
            "type": "conmemorativas",
            "year": "2015",
            "country": "lituania_2"
        },
        {
            "id": 219,
            "type": "conmemorativas",
            "year": "2015",
            "country": "luxemburgo"
        },
        {
            "id": 220,
            "type": "conmemorativas",
            "year": "2015",
            "country": "luxemburgo_2"
        },
        {
            "id": 221,
            "type": "conmemorativas",
            "year": "2015",
            "country": "luxemburgo_3"
        },
        {
            "id": 222,
            "type": "conmemorativas",
            "year": "2015",
            "country": "malta"
        },
        {
            "id": 223,
            "type": "conmemorativas",
            "year": "2015",
            "country": "malta_2"
        },
        {
            "id": 224,
            "type": "conmemorativas",
            "year": "2015",
            "country": "malta_3"
        },
        {
            "id": 225,
            "type": "conmemorativas",
            "year": "2015",
            "country": "monaco"
        },
        {
            "id": 226,
            "type": "conmemorativas",
            "year": "2015",
            "country": "paises_bajos"
        },
        {
            "id": 227,
            "type": "conmemorativas",
            "year": "2015",
            "country": "portugal"
        },
        {
            "id": 228,
            "type": "conmemorativas",
            "year": "2015",
            "country": "portugal_2"
        },
        {
            "id": 229,
            "type": "conmemorativas",
            "year": "2015",
            "country": "portugal_2_3"
        },
        {
            "id": 230,
            "type": "conmemorativas",
            "year": "2015",
            "country": "san_marino"
        },
        {
            "id": 231,
            "type": "conmemorativas",
            "year": "2015",
            "country": "san_marino_2"
        },
        {
            "id": 232,
            "type": "conmemorativas",
            "year": "2015",
            "country": "vaticano"
        },
        {
            "id": 233,
            "type": "conmemorativas",
            "year": "2016",
            "country": "alemania"
        },
        {
            "id": 234,
            "type": "conmemorativas",
            "year": "2016",
            "country": "andorra"
        },
        {
            "id": 235,
            "type": "conmemorativas",
            "year": "2016",
            "country": "andorra_2"
        },
        {
            "id": 236,
            "type": "conmemorativas",
            "year": "2016",
            "country": "austria"
        },
        {
            "id": 237,
            "type": "conmemorativas",
            "year": "2016",
            "country": "belgica"
        },
        {
            "id": 238,
            "type": "conmemorativas",
            "year": "2016",
            "country": "belgica_2"
        },
        {
            "id": 239,
            "type": "conmemorativas",
            "year": "2016",
            "country": "eslovaquia"
        },
        {
            "id": 240,
            "type": "conmemorativas",
            "year": "2016",
            "country": "eslovenia"
        },
        {
            "id": 241,
            "type": "conmemorativas",
            "year": "2016",
            "country": "españa"
        },
        {
            "id": 242,
            "type": "conmemorativas",
            "year": "2016",
            "country": "estonia"
        },
        {
            "id": 243,
            "type": "conmemorativas",
            "year": "2016",
            "country": "finlandia"
        },
        {
            "id": 244,
            "type": "conmemorativas",
            "year": "2016",
            "country": "finlandia_2"
        },
        {
            "id": 245,
            "type": "conmemorativas",
            "year": "2016",
            "country": "francia"
        },
        {
            "id": 246,
            "type": "conmemorativas",
            "year": "2016",
            "country": "francia_2"
        },
        {
            "id": 247,
            "type": "conmemorativas",
            "year": "2016",
            "country": "grecia"
        },
        {
            "id": 248,
            "type": "conmemorativas",
            "year": "2016",
            "country": "grecia_2"
        },
        {
            "id": 249,
            "type": "conmemorativas",
            "year": "2016",
            "country": "irlanda"
        },
        {
            "id": 250,
            "type": "conmemorativas",
            "year": "2016",
            "country": "italia"
        },
        {
            "id": 251,
            "type": "conmemorativas",
            "year": "2016",
            "country": "italia_2"
        },
        {
            "id": 252,
            "type": "conmemorativas",
            "year": "2016",
            "country": "letonia"
        },
        {
            "id": 253,
            "type": "conmemorativas",
            "year": "2016",
            "country": "letonia_2"
        },
        {
            "id": 254,
            "type": "conmemorativas",
            "year": "2016",
            "country": "lituania"
        },
        {
            "id": 255,
            "type": "conmemorativas",
            "year": "2016",
            "country": "luxemburgo"
        },
        {
            "id": 256,
            "type": "conmemorativas",
            "year": "2016",
            "country": "malta"
        },
        {
            "id": 257,
            "type": "conmemorativas",
            "year": "2016",
            "country": "malta_2"
        },
        {
            "id": 258,
            "type": "conmemorativas",
            "year": "2016",
            "country": "monaco"
        },
        {
            "id": 259,
            "type": "conmemorativas",
            "year": "2016",
            "country": "portugal"
        },
        {
            "id": 260,
            "type": "conmemorativas",
            "year": "2016",
            "country": "portugal_2"
        },
        {
            "id": 261,
            "type": "conmemorativas",
            "year": "2016",
            "country": "san_marino"
        },
        {
            "id": 262,
            "type": "conmemorativas",
            "year": "2016",
            "country": "san_marino_2"
        },
        {
            "id": 263,
            "type": "conmemorativas",
            "year": "2016",
            "country": "vaticano"
        },
        {
            "id": 264,
            "type": "conmemorativas",
            "year": "2016",
            "country": "vaticano_2"
        },
        {
            "id": 265,
            "type": "conmemorativas",
            "year": "2017",
            "country": "alemania"
        },
        {
            "id": 266,
            "type": "conmemorativas",
            "year": "2017",
            "country": "andorra"
        },
        {
            "id": 267,
            "type": "conmemorativas",
            "year": "2017",
            "country": "andorra_2"
        },
        {
            "id": 268,
            "type": "conmemorativas",
            "year": "2017",
            "country": "belgica"
        },
        {
            "id": 269,
            "type": "conmemorativas",
            "year": "2017",
            "country": "belgica_2"
        },
        {
            "id": 270,
            "type": "conmemorativas",
            "year": "2017",
            "country": "chipre"
        },
        {
            "id": 271,
            "type": "conmemorativas",
            "year": "2017",
            "country": "eslovaquia"
        },
        {
            "id": 272,
            "type": "conmemorativas",
            "year": "2017",
            "country": "eslovenia"
        },
        {
            "id": 273,
            "type": "conmemorativas",
            "year": "2017",
            "country": "españa"
        },
        {
            "id": 274,
            "type": "conmemorativas",
            "year": "2017",
            "country": "estonia"
        },
        {
            "id": 275,
            "type": "conmemorativas",
            "year": "2017",
            "country": "finlandia"
        },
        {
            "id": 276,
            "type": "conmemorativas",
            "year": "2017",
            "country": "finlandia_2"
        },
        {
            "id": 277,
            "type": "conmemorativas",
            "year": "2017",
            "country": "francia"
        },
        {
            "id": 278,
            "type": "conmemorativas",
            "year": "2017",
            "country": "francia_2"
        },
        {
            "id": 279,
            "type": "conmemorativas",
            "year": "2017",
            "country": "grecia"
        },
        {
            "id": 280,
            "type": "conmemorativas",
            "year": "2017",
            "country": "grecia_2"
        },
        {
            "id": 281,
            "type": "conmemorativas",
            "year": "2017",
            "country": "italia"
        },
        {
            "id": 282,
            "type": "conmemorativas",
            "year": "2017",
            "country": "italia_2"
        },
        {
            "id": 283,
            "type": "conmemorativas",
            "year": "2017",
            "country": "letonia"
        },
        {
            "id": 284,
            "type": "conmemorativas",
            "year": "2017",
            "country": "letonia_2"
        },
        {
            "id": 285,
            "type": "conmemorativas",
            "year": "2017",
            "country": "lituania"
        },
        {
            "id": 286,
            "type": "conmemorativas",
            "year": "2017",
            "country": "luxemburgo"
        },
        {
            "id": 287,
            "type": "conmemorativas",
            "year": "2017",
            "country": "luxemburgo_2"
        },
        {
            "id": 288,
            "type": "conmemorativas",
            "year": "2017",
            "country": "malta"
        },
        {
            "id": 289,
            "type": "conmemorativas",
            "year": "2017",
            "country": "malta_2"
        },
        {
            "id": 290,
            "type": "conmemorativas",
            "year": "2017",
            "country": "monaco"
        },
        {
            "id": 291,
            "type": "conmemorativas",
            "year": "2017",
            "country": "portugal"
        },
        {
            "id": 292,
            "type": "conmemorativas",
            "year": "2017",
            "country": "portugal_2"
        },
        {
            "id": 293,
            "type": "conmemorativas",
            "year": "2017",
            "country": "san_marino"
        },
        {
            "id": 294,
            "type": "conmemorativas",
            "year": "2017",
            "country": "san_marino_2"
        },
        {
            "id": 295,
            "type": "conmemorativas",
            "year": "2017",
            "country": "vaticano"
        },
        {
            "id": 296,
            "type": "conmemorativas",
            "year": "2017",
            "country": "vaticano_2"
        },
        {
            "id": 297,
            "type": "conmemorativas",
            "year": "2018",
            "country": "alemania"
        },
        {
            "id": 298,
            "type": "conmemorativas",
            "year": "2018",
            "country": "alemania_2"
        },
        {
            "id": 299,
            "type": "conmemorativas",
            "year": "2018",
            "country": "andorra"
        },
        {
            "id": 300,
            "type": "conmemorativas",
            "year": "2018",
            "country": "andorra_2"
        },
        {
            "id": 301,
            "type": "conmemorativas",
            "year": "2018",
            "country": "austria"
        },
        {
            "id": 302,
            "type": "conmemorativas",
            "year": "2018",
            "country": "belgica"
        },
        {
            "id": 303,
            "type": "conmemorativas",
            "year": "2018",
            "country": "belgica_2"
        },
        {
            "id": 304,
            "type": "conmemorativas",
            "year": "2018",
            "country": "eslovaquia"
        },
        {
            "id": 305,
            "type": "conmemorativas",
            "year": "2018",
            "country": "eslovenia"
        },
        {
            "id": 306,
            "type": "conmemorativas",
            "year": "2018",
            "country": "españa"
        },
        {
            "id": 307,
            "type": "conmemorativas",
            "year": "2018",
            "country": "españa_2"
        },
        {
            "id": 308,
            "type": "conmemorativas",
            "year": "2018",
            "country": "estonia"
        },
        {
            "id": 309,
            "type": "conmemorativas",
            "year": "2018",
            "country": "estonia_2"
        },
        {
            "id": 310,
            "type": "conmemorativas",
            "year": "2018",
            "country": "finlandia"
        },
        {
            "id": 311,
            "type": "conmemorativas",
            "year": "2018",
            "country": "finlandia_2"
        },
        {
            "id": 312,
            "type": "conmemorativas",
            "year": "2018",
            "country": "francia"
        },
        {
            "id": 313,
            "type": "conmemorativas",
            "year": "2018",
            "country": "francia_2"
        },
        {
            "id": 314,
            "type": "conmemorativas",
            "year": "2018",
            "country": "grecia"
        },
        {
            "id": 315,
            "type": "conmemorativas",
            "year": "2018",
            "country": "grecia_2"
        },
        {
            "id": 316,
            "type": "conmemorativas",
            "year": "2018",
            "country": "italia"
        },
        {
            "id": 317,
            "type": "conmemorativas",
            "year": "2018",
            "country": "italia_2"
        },
        {
            "id": 318,
            "type": "conmemorativas",
            "year": "2018",
            "country": "letonia"
        },
        {
            "id": 319,
            "type": "conmemorativas",
            "year": "2018",
            "country": "letonia_2"
        },
        {
            "id": 320,
            "type": "conmemorativas",
            "year": "2018",
            "country": "lituania"
        },
        {
            "id": 321,
            "type": "conmemorativas",
            "year": "2018",
            "country": "lituania_2"
        },
        {
            "id": 322,
            "type": "conmemorativas",
            "year": "2018",
            "country": "luxemburgo"
        },
        {
            "id": 323,
            "type": "conmemorativas",
            "year": "2018",
            "country": "luxemburgo_2"
        },
        {
            "id": 324,
            "type": "conmemorativas",
            "year": "2018",
            "country": "malta"
        },
        {
            "id": 325,
            "type": "conmemorativas",
            "year": "2018",
            "country": "malta_2"
        },
        {
            "id": 326,
            "type": "conmemorativas",
            "year": "2018",
            "country": "monaco"
        },
        {
            "id": 327,
            "type": "conmemorativas",
            "year": "2018",
            "country": "portugal"
        },
        {
            "id": 328,
            "type": "conmemorativas",
            "year": "2018",
            "country": "portugal_2"
        },
        {
            "id": 329,
            "type": "conmemorativas",
            "year": "2018",
            "country": "san_marino"
        },
        {
            "id": 330,
            "type": "conmemorativas",
            "year": "2018",
            "country": "san_marino_2"
        },
        {
            "id": 331,
            "type": "conmemorativas",
            "year": "2018",
            "country": "vaticano"
        },
        {
            "id": 332,
            "type": "conmemorativas",
            "year": "2018",
            "country": "vaticano_2"
        },
        {
            "id": 333,
            "type": "conmemorativas",
            "year": "2019",
            "country": "alemania"
        },
        {
            "id": 334,
            "type": "conmemorativas",
            "year": "2019",
            "country": "alemania_2"
        },
        {
            "id": 335,
            "type": "conmemorativas",
            "year": "2019",
            "country": "andorra"
        },
        {
            "id": 336,
            "type": "conmemorativas",
            "year": "2019",
            "country": "andorra_2"
        },
        {
            "id": 337,
            "type": "conmemorativas",
            "year": "2019",
            "country": "belgica"
        },
        {
            "id": 338,
            "type": "conmemorativas",
            "year": "2019",
            "country": "belgica_2"
        },
        {
            "id": 339,
            "type": "conmemorativas",
            "year": "2019",
            "country": "eslovaquia"
        },
        {
            "id": 340,
            "type": "conmemorativas",
            "year": "2019",
            "country": "eslovenia"
        },
        {
            "id": 341,
            "type": "conmemorativas",
            "year": "2019",
            "country": "españa"
        },
        {
            "id": 342,
            "type": "conmemorativas",
            "year": "2019",
            "country": "estonia"
        },
        {
            "id": 343,
            "type": "conmemorativas",
            "year": "2019",
            "country": "estonia_2"
        },
        {
            "id": 344,
            "type": "conmemorativas",
            "year": "2019",
            "country": "finlandia_2"
        },
        {
            "id": 345,
            "type": "conmemorativas",
            "year": "2019",
            "country": "francia"
        },
        {
            "id": 346,
            "type": "conmemorativas",
            "year": "2019",
            "country": "francia_2"
        },
        {
            "id": 347,
            "type": "conmemorativas",
            "year": "2019",
            "country": "grecia"
        },
        {
            "id": 348,
            "type": "conmemorativas",
            "year": "2019",
            "country": "grecia_2"
        },
        {
            "id": 349,
            "type": "conmemorativas",
            "year": "2019",
            "country": "irlanda"
        },
        {
            "id": 350,
            "type": "conmemorativas",
            "year": "2019",
            "country": "italia"
        },
        {
            "id": 351,
            "type": "conmemorativas",
            "year": "2019",
            "country": "letonia"
        },
        {
            "id": 352,
            "type": "conmemorativas",
            "year": "2019",
            "country": "lituania"
        },
        {
            "id": 353,
            "type": "conmemorativas",
            "year": "2019",
            "country": "lituania_2"
        },
        {
            "id": 354,
            "type": "conmemorativas",
            "year": "2019",
            "country": "luxemburgo"
        },
        {
            "id": 355,
            "type": "conmemorativas",
            "year": "2019",
            "country": "luxemburgo_2"
        },
        {
            "id": 356,
            "type": "conmemorativas",
            "year": "2019",
            "country": "malta"
        },
        {
            "id": 357,
            "type": "conmemorativas",
            "year": "2019",
            "country": "malta_2"
        },
        {
            "id": 358,
            "type": "conmemorativas",
            "year": "2019",
            "country": "monaco"
        },
        {
            "id": 359,
            "type": "conmemorativas",
            "year": "2019",
            "country": "portugal"
        },
        {
            "id": 360,
            "type": "conmemorativas",
            "year": "2019",
            "country": "portugal_2"
        },
        {
            "id": 361,
            "type": "conmemorativas",
            "year": "2019",
            "country": "san_marino"
        },
        {
            "id": 362,
            "type": "conmemorativas",
            "year": "2019",
            "country": "san_marino_2"
        },
        {
            "id": 363,
            "type": "conmemorativas",
            "year": "2019",
            "country": "vaticano"
        },
        {
            "id": 364,
            "type": "conmemorativas",
            "year": "2019",
            "country": "vaticano_2"
        },
        {
            "id": 365,
            "type": "conmemorativas",
            "year": "2020",
            "country": "alemania"
        },
        {
            "id": 366,
            "type": "conmemorativas",
            "year": "2020",
            "country": "alemania_2"
        },
        {
            "id": 367,
            "type": "conmemorativas",
            "year": "2020",
            "country": "andorra"
        },
        {
            "id": 368,
            "type": "conmemorativas",
            "year": "2020",
            "country": "andorra_2"
        },
        {
            "id": 369,
            "type": "conmemorativas",
            "year": "2020",
            "country": "belgica"
        },
        {
            "id": 370,
            "type": "conmemorativas",
            "year": "2020",
            "country": "belgica_2"
        },
        {
            "id": 371,
            "type": "conmemorativas",
            "year": "2020",
            "country": "chipre"
        },
        {
            "id": 372,
            "type": "conmemorativas",
            "year": "2020",
            "country": "eslovaquia"
        },
        {
            "id": 373,
            "type": "conmemorativas",
            "year": "2020",
            "country": "eslovenia"
        },
        {
            "id": 374,
            "type": "conmemorativas",
            "year": "2020",
            "country": "españa"
        },
        {
            "id": 375,
            "type": "conmemorativas",
            "year": "2020",
            "country": "estonia"
        },
        {
            "id": 376,
            "type": "conmemorativas",
            "year": "2020",
            "country": "estonia_2"
        },
        {
            "id": 377,
            "type": "conmemorativas",
            "year": "2020",
            "country": "finlandia"
        },
        {
            "id": 378,
            "type": "conmemorativas",
            "year": "2020",
            "country": "finlandia_2"
        },
        {
            "id": 379,
            "type": "conmemorativas",
            "year": "2020",
            "country": "francia"
        },
        {
            "id": 380,
            "type": "conmemorativas",
            "year": "2020",
            "country": "francia_2"
        },
        {
            "id": 381,
            "type": "conmemorativas",
            "year": "2020",
            "country": "grecia"
        },
        {
            "id": 382,
            "type": "conmemorativas",
            "year": "2020",
            "country": "grecia_2"
        },
        {
            "id": 383,
            "type": "conmemorativas",
            "year": "2020",
            "country": "italia"
        },
        {
            "id": 384,
            "type": "conmemorativas",
            "year": "2020",
            "country": "italia_2"
        },
        {
            "id": 385,
            "type": "conmemorativas",
            "year": "2020",
            "country": "letonia"
        },
        {
            "id": 386,
            "type": "conmemorativas",
            "year": "2020",
            "country": "lituania"
        },
        {
            "id": 387,
            "type": "conmemorativas",
            "year": "2020",
            "country": "lituania_2"
        },
        {
            "id": 388,
            "type": "conmemorativas",
            "year": "2020",
            "country": "luxemburgo"
        },
        {
            "id": 389,
            "type": "conmemorativas",
            "year": "2020",
            "country": "luxemburgo_2"
        },
        {
            "id": 390,
            "type": "conmemorativas",
            "year": "2020",
            "country": "malta"
        },
        {
            "id": 391,
            "type": "conmemorativas",
            "year": "2020",
            "country": "malta_2"
        },
        {
            "id": 392,
            "type": "conmemorativas",
            "year": "2020",
            "country": "monaco"
        },
        {
            "id": 393,
            "type": "conmemorativas",
            "year": "2020",
            "country": "portugal"
        },
        {
            "id": 394,
            "type": "conmemorativas",
            "year": "2020",
            "country": "portugal_2"
        },
        {
            "id": 395,
            "type": "conmemorativas",
            "year": "2020",
            "country": "san_marino"
        },
        {
            "id": 396,
            "type": "conmemorativas",
            "year": "2020",
            "country": "san_marino_2"
        },
        {
            "id": 397,
            "type": "conmemorativas",
            "year": "2020",
            "country": "vaticano"
        },
        {
            "id": 398,
            "type": "conmemorativas",
            "year": "2020",
            "country": "vaticano_2"
        },
        {
            "id": 399,
            "type": "conmemorativas",
            "year": "2021",
            "country": "alemania"
        },
        {
            "id": 400,
            "type": "conmemorativas",
            "year": "2021",
            "country": "andorra"
        },
        {
            "id": 401,
            "type": "conmemorativas",
            "year": "2021",
            "country": "andorra_2"
        },
        {
            "id": 402,
            "type": "conmemorativas",
            "year": "2021",
            "country": "belgica"
        },
        {
            "id": 403,
            "type": "conmemorativas",
            "year": "2021",
            "country": "belgica_2"
        },
        {
            "id": 404,
            "type": "conmemorativas",
            "year": "2021",
            "country": "eslovaquia"
        },
        {
            "id": 405,
            "type": "conmemorativas",
            "year": "2021",
            "country": "eslovenia"
        },
        {
            "id": 406,
            "type": "conmemorativas",
            "year": "2021",
            "country": "españa"
        },
        {
            "id": 407,
            "type": "conmemorativas",
            "year": "2021",
            "country": "estonia"
        },
        {
            "id": 408,
            "type": "conmemorativas",
            "year": "2021",
            "country": "estonia_2"
        },
        {
            "id": 409,
            "type": "conmemorativas",
            "year": "2021",
            "country": "finlandia"
        },
        {
            "id": 410,
            "type": "conmemorativas",
            "year": "2021",
            "country": "finlandia_2"
        },
        {
            "id": 411,
            "type": "conmemorativas",
            "year": "2021",
            "country": "francia"
        },
        {
            "id": 412,
            "type": "conmemorativas",
            "year": "2021",
            "country": "francia_2"
        },
        {
            "id": 413,
            "type": "conmemorativas",
            "year": "2021",
            "country": "grecia"
        },
        {
            "id": 414,
            "type": "conmemorativas",
            "year": "2021",
            "country": "italia"
        },
        {
            "id": 415,
            "type": "conmemorativas",
            "year": "2021",
            "country": "italia_2"
        },
        {
            "id": 416,
            "type": "conmemorativas",
            "year": "2021",
            "country": "letonia"
        },
        {
            "id": 417,
            "type": "conmemorativas",
            "year": "2021",
            "country": "lituania"
        },
        {
            "id": 418,
            "type": "conmemorativas",
            "year": "2021",
            "country": "lituania_2"
        },
        {
            "id": 419,
            "type": "conmemorativas",
            "year": "2021",
            "country": "luxemburgo"
        },
        {
            "id": 420,
            "type": "conmemorativas",
            "year": "2021",
            "country": "luxemburgo_2"
        },
        {
            "id": 421,
            "type": "conmemorativas",
            "year": "2021",
            "country": "malta"
        },
        {
            "id": 422,
            "type": "conmemorativas",
            "year": "2021",
            "country": "malta_2"
        },
        {
            "id": 423,
            "type": "conmemorativas",
            "year": "2021",
            "country": "monaco"
        },
        {
            "id": 424,
            "type": "conmemorativas",
            "year": "2021",
            "country": "portugal"
        },
        {
            "id": 425,
            "type": "conmemorativas",
            "year": "2021",
            "country": "portugal_2"
        },
        {
            "id": 426,
            "type": "conmemorativas",
            "year": "2021",
            "country": "san_marino"
        },
        {
            "id": 427,
            "type": "conmemorativas",
            "year": "2021",
            "country": "san_marino_2"
        },
        {
            "id": 428,
            "type": "conmemorativas",
            "year": "2021",
            "country": "vaticano"
        },
        {
            "id": 429,
            "type": "conmemorativas",
            "year": "2021",
            "country": "vaticano_2"
        },
        {
            "id": 430,
            "type": "conmemorativas",
            "year": "2022",
            "country": "alemania"
        },
        {
            "id": 431,
            "type": "conmemorativas",
            "year": "2022",
            "country": "eslovenia"
        },
        {
            "id": 432,
            "type": "conmemorativas",
            "year": "2022",
            "country": "francia"
        },
        {
            "id": 433,
            "type": "conmemorativas",
            "year": "2022",
            "country": "italia"
        },
        {
            "id": 434,
            "type": "conmemorativas",
            "year": "2022",
            "country": "italia_2"
        },
        {
            "id": 435,
            "type": "conmemorativas",
            "year": "2022",
            "country": "luxemburgo"
        },
        {
            "id": 436,
            "type": "conmemorativas",
            "year": "2022",
            "country": "luxemburgo_2"
        },
        {
            "id": 437,
            "type": "conmemorativas",
            "year": "2023",
            "country": "alemania"
        },
        {
            "id": 438,
            "type": "normal",
            "year": "0",
            "country": "vaticano"
        },
        {
            "id": 439,
            "type": "normal",
            "year": "2001",
            "country": "finlandia"
        },
        {
            "id": 440,
            "type": "normal",
            "year": "2001",
            "country": "francia"
        },
        {
            "id": 441,
            "type": "normal",
            "year": "2001",
            "country": "monaco"
        },
        {
            "id": 442,
            "type": "normal",
            "year": "2001",
            "country": "paises_bajos"
        },
        {
            "id": 443,
            "type": "normal",
            "year": "2002",
            "country": "grecia"
        },
        {
            "id": 444,
            "type": "normal",
            "year": "2002",
            "country": "italia"
        },
        {
            "id": 445,
            "type": "normal",
            "year": "2002",
            "country": "portugal"
        },
        {
            "id": 446,
            "type": "normal",
            "year": "2002",
            "country": "vaticano"
        },
        {
            "id": 447,
            "type": "normal",
            "year": "2003",
            "country": "alemania"
        },
        {
            "id": 448,
            "type": "normal",
            "year": "2003",
            "country": "austria"
        },
        {
            "id": 449,
            "type": "normal",
            "year": "2003",
            "country": "españa"
        },
        {
            "id": 450,
            "type": "normal",
            "year": "2003",
            "country": "irlanda"
        },
        {
            "id": 451,
            "type": "normal",
            "year": "2004",
            "country": "belgica"
        },
        {
            "id": 452,
            "type": "normal",
            "year": "2004",
            "country": "luxemburgo"
        },
        {
            "id": 453,
            "type": "normal",
            "year": "2006",
            "country": "monaco"
        },
        {
            "id": 454,
            "type": "normal",
            "year": "2007",
            "country": "eslovenia"
        },
        {
            "id": 455,
            "type": "normal",
            "year": "2008",
            "country": "belgica"
        },
        {
            "id": 456,
            "type": "normal",
            "year": "2008",
            "country": "chipre"
        },
        {
            "id": 457,
            "type": "normal",
            "year": "2008",
            "country": "malta"
        },
        {
            "id": 458,
            "type": "normal",
            "year": "2009",
            "country": "eslovaquia"
        },
        {
            "id": 459,
            "type": "normal",
            "year": "2010",
            "country": "san_marino"
        },
        {
            "id": 460,
            "type": "normal",
            "year": "2011",
            "country": "estonia"
        },
        {
            "id": 461,
            "type": "normal",
            "year": "2013",
            "country": "vaticano"
        },
        {
            "id": 462,
            "type": "normal",
            "year": "2014",
            "country": "belgica"
        },
        {
            "id": 463,
            "type": "normal",
            "year": "2014",
            "country": "españa"
        },
        {
            "id": 464,
            "type": "normal",
            "year": "2014",
            "country": "letonia"
        },
        {
            "id": 465,
            "type": "normal",
            "year": "2014",
            "country": "paises_bajos"
        },
        {
            "id": 466,
            "type": "normal",
            "year": "2015",
            "country": "españa"
        },
        {
            "id": 467,
            "type": "normal",
            "year": "2015",
            "country": "lituania"
        },
        {
            "id": 468,
            "type": "normal",
            "year": "2016",
            "country": "vaticano"
        },
        {
            "id": 469,
            "type": "normal",
            "year": "2017",
            "country": "san_marino"
        },
        {
            "id": 470,
            "type": "normal",
            "year": "2017",
            "country": "vaticano"
        },
        {
            "id": 471,
            "type": "normal",
            "year": "2022",
            "country": "francia"
        },
        {
            "id": 472,
            "type": "normal",
            "year": "2023",
            "country": "croacia"
        }
    ]
}